pykeepass_rs-0.1.15.dist-info/METADATA
pykeepass_rs-0.1.15.dist-info/WHEEL
pykeepass_rs/__init__.py
pykeepass_rs/__init__.pyi
pykeepass_rs/py.typed
pykeepass_rs/pykeepass_rs.cpython-38-x86_64-linux-gnu.so
pykeepass_rs-0.1.15.dist-info/RECORD
