Metadata-Version: 2.1
Name: pykeepass-rs
Version: 0.1.15
Author: david <davidventura27@gmail.com>
Author-email: david <davidventura27@gmail.com>
